community_sift/__init__.py
community_sift/communitysift.py
communitysift-0.0.0.dist-info/DESCRIPTION.rst
communitysift-0.0.0.dist-info/METADATA
communitysift-0.0.0.dist-info/RECORD
communitysift-0.0.0.dist-info/WHEEL
communitysift-0.0.0.dist-info/metadata.json
communitysift-0.0.0.dist-info/top_level.txt
python/__init__.py
utils/__init__.py
utils/constants.py
