Metadata-Version: 2.0
Name: communitysift
Version: 0.0.0
Summary: Community Sift is a SaaS based, dynamic and real time Chat Filtering Tool
Home-page: https://communitysift.com/
Author: CommunitySift
Author-email: demo@communitysift.com
License: UNKNOWN
Platform: UNKNOWN
Classifier: Development Status :: 3 - Alpha
Classifier: Intended Audience :: Developers
Classifier: Programming Language :: Python
Classifier: Operating System :: OS Independent
Classifier: Topic :: Internet :: WWW/HTTP
Classifier: Topic :: Software Development :: Libraries :: Python Modules
Requires-Dist: ConfigParser
Requires-Dist: requests
